{
  "bio_id": "109",
  "source": "ansari",
  "death_date": "",
  "geographical_locations": [
    {
      "place": "یزد",
      "context": "lived",
      "full_text": "در یزد"
    }
  ],
  "isnads": [
    {
      "chain": [],
      "type": "single_informant",
      "full_text": "شیخ الاسلام گفت:",
      "refers_to_previous": false
    },
    {
      "chain": [],
      "type": "single_informant",
      "full_text": "شیخ الاسلام گفت:",
      "refers_to_previous": false
    },
    {
      "chain": [],
      "type": "single_informant",
      "full_text": "شیخ الاسلام گفت:",
      "refers_to_previous": false
    },
    {
      "chain": [
        {
          "name": "بوحاتم",
          "person_id": 828,
          "canonical_name": "أبو حاتم العطّار البصري",
          "has_id": 109,
          "subj_added": false
        }
      ],
      "type": "single_informant",
      "full_text": "و هم بوحاتم گوید:",
      "refers_to_previous": false
    },
    {
      "chain": [
        {
          "name": "بوسعید زیادی",
          "person_id": 887,
          "canonical_name": "أبو سعيد زيادي",
          "has_id": NaN,
          "subj_added": false
        },
        {
          "name": "",
          "person_id": 828,
          "canonical_name": "أبو حاتم العطّار البصري",
          "has_id": 109,
          "subj_added": true
        }
      ],
      "type": "single_informant",
      "full_text": "بوسعید زیادی گوید:",
      "refers_to_previous": false
    }
  ],
  "relationships": {
    "teachers": [
      {
        "name": "بو سعید خراز",
        "relationship_type": "student_of",
        "relationship_phrase": "استاد",
        "full_text": "«و استاد» بو سعید خراز و جنید است",
        "person_id": 877,
        "canonical_name": "أبو سعيد الخراز",
        "has_id": 123
      },
      {
        "name": "جنید",
        "relationship_type": "student_of",
        "relationship_phrase": "استاد",
        "full_text": "«و استاد» بو سعید خراز و جنید است",
        "person_id": 595,
        "canonical_name": "أبو القاسم الجنيد بن محمد البغدادي",
        "has_id": 228
      }
    ],
    "students": [
      {
        "name": "ابوتراب نخشبی",
        "relationship_type": "teacher_of",
        "relationship_phrase": "از استادان",
        "full_text": "از استادان ابوتراب نخشبی بوده است",
        "person_id": 796,
        "canonical_name": "أبو تراب عسكر بن الحصين النخشبي",
        "has_id": 388
      }
    ],
    "companions": [
      {
        "name": "بوتراب",
        "relationship_type": "peer",
        "relationship_phrase": "از اقران",
        "full_text": "از اقران بوتراب بوده است",
        "person_id": 796,
        "canonical_name": "أبو تراب عسكر بن الحصين النخشبي",
        "has_id": 388
      },
      {
        "name": "بوتراب",
        "relationship_type": "peer",
        "relationship_phrase": "باوی سفرکرده است",
        "full_text": "باوی سفرکرده است",
        "person_id": 796,
        "canonical_name": "أبو تراب عسكر بن الحصين النخشبي",
        "has_id": 388
      }
    ]
  },
  "associates": [
    {
      "name": "شیخ الاسلام",
      "relationship_type": "narrator",
      "full_text": "شیخ الاسلام گفت:",
      "person_id": 650,
      "canonical_name": "أبو إسماعيل عبد الله الانصاري الهروي",
      "has_id": 36
    },
    {
      "name": "بوسعید زیادی",
      "relationship_type": "narrator",
      "full_text": "بوسعید زیادی گوید:",
      "person_id": 887,
      "canonical_name": "أبو سعيد زيادي",
      "has_id": NaN
    },
    {
      "name": "مردی",
      "relationship_type": "interlocutor",
      "full_text": "مردی فرا در سرای بوحاتم عطار شد در یزد",
      "person_id": 288,
      "canonical_name": "امرأة أبي يزيد البسطامي",
      "has_id": NaN
    },
    {
      "name": "محمد وهب",
      "relationship_type": "mentioned_in_anecdote",
      "full_text": "گویند کی محمد وهب بود ابویعقوب الزیات در بزد",
      "person_id": 2528,
      "canonical_name": "محمد بن وهب",
      "has_id": NaN
    },
    {
      "name": "ابویعقوب الزیات",
      "relationship_type": "mentioned_in_anecdote",
      "full_text": "گویند کی محمد وهب بود ابویعقوب الزیات در بزد",
      "person_id": 1199,
      "canonical_name": "أبو يعقوب الزيات",
      "has_id": 436
    },
    {
      "name": "شبلی",
      "relationship_type": "mentioned_in_anecdote",
      "full_text": "شبلی بخواب دید",
      "person_id": 699,
      "canonical_name": "أبو بكر الشبلي",
      "has_id": 376
    },
    {
      "name": "خضر ﷷ",
      "relationship_type": "mentioned_in_anecdote",
      "full_text": "خضر ﷷ ناگاه برو درآمد",
      "person_id": 166,
      "canonical_name": "الخضر",
      "has_id": NaN
    },
    {
      "name": "الیاس",
      "relationship_type": "mentioned_in_anecdote",
      "full_text": "گفت: او چنان است او برادر منست الیاس.",
      "person_id": 285,
      "canonical_name": "الياس",
      "has_id": NaN
    },
    {
      "name": "موسی",
      "relationship_type": "mentioned_in_anecdote",
      "full_text": "چنانک موسی بر من منکر شد.",
      "person_id": 2627,
      "canonical_name": "موسي",
      "has_id": NaN
    }
  ]
}